loducode_utils/__init__.py
loducode_utils/admin.py
loducode_utils/apps.py
loducode_utils/serializers.py
loducode_utils/tasks.py
loducode_utils/urls.py
loducode_utils/urls_api.py
loducode_utils/utils.py
loducode_utils/views_api.py
loducode_utils/migrations/0001_initial.py
loducode_utils/migrations/0002_auto_20210318_1005.py
loducode_utils/migrations/0003_auto_20210701_0220.py
loducode_utils/migrations/0004_city_icon.py
loducode_utils/migrations/0005_alter_city_created_by_alter_city_modified_by.py
loducode_utils/migrations/__init__.py
loducode_utils/models/__init__.py
loducode_utils/models/audit.py
loducode_utils/models/city.py
loducode_utils/models/payment_record.py
loducode_utils-1.5.10.dist-info/LICENSE.txt
loducode_utils-1.5.10.dist-info/METADATA
loducode_utils-1.5.10.dist-info/WHEEL
loducode_utils-1.5.10.dist-info/top_level.txt
loducode_utils-1.5.10.dist-info/RECORD
