Metadata-Version: 2.1
Name: loducode_utils
Version: 1.5.10
Summary: Basic components for the development of loducode s.a.s.
Home-page: https://github.com/UnTalDulcey/loducode_utils
Download-URL: https://github.com/UnTalDulcey/loducode_utils/tarball/1.5.10
Author: Cristian Dulcey
Author-email: cristian@loducode.com
Keywords: utils,loducode_utils,loducode
License-File: LICENSE.txt
Requires-Dist: markdown >=3.2.2
Requires-Dist: MarkupPy >=1.14
Requires-Dist: MarkupSafe >=1.1.1
Requires-Dist: djangorestframework >=3.11.2
Requires-Dist: django-filter >=2.2.0
Requires-Dist: django-rest-swagger >=2.2.0
Requires-Dist: django >=2.0
Requires-Dist: django-crum >=0.7.5
Requires-Dist: celery >=4.4.2
Requires-Dist: django-import-export >=2.1.0
Requires-Dist: slackclient >=2.9.3
